smirnybot9001/__init__.py
smirnybot9001/chatbot.py
smirnybot9001/color_table.py
smirnybot9001/config.py
smirnybot9001/overlay.py
smirnybot9001/smirnyboot9001.py
smirnybot9001/util.py
smirnybot9001/data/__init__.py
smirnybot9001/data/happy-ending.wav
smirnybot9001/data/sample.conf
smirnybot9001-0.0.6.dist-info/METADATA
smirnybot9001-0.0.6.dist-info/WHEEL
smirnybot9001-0.0.6.dist-info/entry_points.txt
smirnybot9001-0.0.6.dist-info/licenses/LICENSE
smirnybot9001-0.0.6.dist-info/RECORD
