Metadata-Version: 2.1
Name: smirnybot9001
Version: 0.0.6
Summary: A twitch chatbot for displaying LEGO sets, minifigs and parts on an HTML overlay
Project-URL: Homepage, https://github.com/BricksMental/smirnybot9001
Project-URL: Bug Tracker, https://github.com/BricksMental/smirnybot9001/issues
Author-email: Bricks Mental <bricks.mental@gmail.com>
License:                     GNU GENERAL PUBLIC LICENSE
License-File: LICENSE
Classifier: Development Status :: 3 - Alpha
Classifier: License :: OSI Approved :: GNU General Public License v3 (GPLv3)
Classifier: Operating System :: OS Independent
Classifier: Programming Language :: Python :: 3 :: Only
Requires-Python: >=3.8
Requires-Dist: beautifulsoup4
Requires-Dist: fake-user-agent
Requires-Dist: remi
Requires-Dist: requests
Requires-Dist: rich
Requires-Dist: tomlkit
Requires-Dist: twitchio
Requires-Dist: typer
